hedera_cli/__init__.py
hedera_cli/_version.py
hedera_cli/check_java.py
hedera_cli/hedera_cli.py
hedera_cli/main.py
hedera_cli/price.py
hedera_cli-0.1.2.post1.dist-info/METADATA
hedera_cli-0.1.2.post1.dist-info/WHEEL
hedera_cli-0.1.2.post1.dist-info/entry_points.txt
hedera_cli-0.1.2.post1.dist-info/top_level.txt
hedera_cli-0.1.2.post1.dist-info/RECORD
