Metadata-Version: 2.1
Name: hedera-cli
Version: 0.1.2.post1
Summary: Hedera CLI in Python
Home-page: https://github.com/wensheng/hedera-cli-py
Author: Wensheng Wang
Author-email: wenshengwang@gmail.com
License: UNKNOWN
Project-URL: Bug Tracker, https://github.com/wensheng/hedera-cli-py/issues
Platform: UNKNOWN
Classifier: Programming Language :: Python :: 3
Classifier: License :: OSI Approved :: Apache Software License
Classifier: Operating System :: OS Independent
Requires-Python: >=3.6
Requires-Dist: hedera-sdk-py (>=2.0.9)
Requires-Dist: colorama (>=0.4.4)
Requires-Dist: python-dotenv (>=0.18.0)
Requires-Dist: requests (>=2.19.1)
